pyflame/__init__.py
pyflame/__main__.py
pyflame/exceptions.py
pyflame/ipython.py
pyflame/render.py
pyflame/runner.py
pyflame/sampler.py
pyflame/stack.py
pyflame/djdt/__init__.py
pyflame/djdt/panel.py
pyflame/djdt/settings.py
pyflame/templates/pyflame/panel.html
pyflame-0.3.2.dist-info/LICENSE
pyflame-0.3.2.dist-info/METADATA
pyflame-0.3.2.dist-info/WHEEL
pyflame-0.3.2.dist-info/top_level.txt
pyflame-0.3.2.dist-info/RECORD
