Metadata-Version: 2.1
Name: pyflame
Version: 0.3.2
Summary: A Flamegraph generator for Python
Home-page: https://gitlab.com/living180/pyflame
Author: Daniel Harding
Author-email: dharding@living180.net
Classifier: Development Status :: 4 - Beta
Classifier: Environment :: Console
Classifier: Framework :: Django
Classifier: Framework :: Jupyter
Classifier: Intended Audience :: Developers
Classifier: License :: OSI Approved :: MIT License
Classifier: Programming Language :: Python :: 3
Classifier: Programming Language :: Python :: 3 :: Only
Classifier: Programming Language :: Python :: 3.7
Classifier: Programming Language :: Python :: 3.8
Classifier: Programming Language :: Python :: 3.9
Classifier: Programming Language :: Python :: 3.10
Classifier: Operating System :: OS Independent
Requires-Python: >=3.7
License-File: LICENSE
Provides-Extra: jupyter
Requires-Dist: ipython; extra == "jupyter"
Requires-Dist: traitlets>=5; extra == "jupyter"
Provides-Extra: django
Requires-Dist: django>=3.2; extra == "django"
Requires-Dist: django-debug-toolbar; extra == "django"
